{
  "$schema": "https://developer.microsoft.com/json-schemas/fabric/item/report/definition/visualContainer/2.7.0/schema.json",
  "name": "9a000896cd75f458a77b",
  "position": {
    "x": 450,
    "y": 10,
    "z": 3000,
    "height": 120,
    "width": 200,
    "tabOrder": 3000
  },
  "visual": {
    "visualType": "card",
    "query": {
      "queryState": {
        "Values": {
          "projections": [
            {
              "field": {
                "Aggregation": {
                  "Expression": {
                    "Column": {
                      "Expression": {
                        "SourceRef": {
                          "Entity": "financials"
                        }
                      },
                      "Property": "Sales"
                    }
                  },
                  "Function": 0
                }
              },
              "queryRef": "Sum(financials.Sales)",
              "nativeQueryRef": "Sum of Sales"
            }
          ]
        }
      }
    },
    "objects": {
      "labels": [
        {
          "properties": {
            "fontSize": {
              "expr": {
                "Literal": {
                  "Value": "8D"
                }
              }
            },
            "fontFamily": {
              "expr": {
                "Literal": {
                  "Value": "''Segoe UI', wf_segoe-ui_normal, helvetica, arial, sans-serif'"
                }
              }
            }
          }
        }
      ]
    },
    "visualContainerObjects": {
      "title": [
        {
          "properties": {
            "text": {
              "expr": {
                "Literal": {
                  "Value": "'Stay Put'"
                }
              }
            },
            "fontSize": {
              "expr": {
                "Literal": {
                  "Value": "8D"
                }
              }
            },
            "fontFamily": {
              "expr": {
                "Literal": {
                  "Value": "''Segoe UI', wf_segoe-ui_normal, helvetica, arial, sans-serif'"
                }
              }
            }
          }
        }
      ]
    },
    "drillFilterOtherVisuals": true
  },
  "filterConfig": {
    "filters": [
      {
        "name": "6e1841a8f0463b4e134c",
        "field": {
          "Aggregation": {
            "Expression": {
              "Column": {
                "Expression": {
                  "SourceRef": {
                    "Entity": "financials"
                  }
                },
                "Property": "Sales"
              }
            },
            "Function": 0
          }
        },
        "type": "Advanced"
      }
    ]
  }
}