{
  "$schema": "https://developer.microsoft.com/json-schemas/fabric/item/report/definition/visualContainer/2.7.0/schema.json",
  "name": "b4990625e0e3db194f0c",
  "position": {
    "x": 10,
    "y": 160,
    "z": 8000,
    "height": 260,
    "width": 630,
    "tabOrder": 8000
  },
  "visual": {
    "visualType": "lineChart",
    "query": {
      "queryState": {
        "Category": {
          "projections": [
            {
              "field": {
                "Column": {
                  "Expression": {
                    "SourceRef": {
                      "Entity": "Date"
                    }
                  },
                  "Property": "Year Month Short"
                }
              },
              "queryRef": "Date.Year Month Short",
              "nativeQueryRef": "Year Month Short",
              "active": true
            }
          ]
        },
        "Y": {
          "projections": [
            {
              "field": {
                "Measure": {
                  "Expression": {
                    "SourceRef": {
                      "Entity": "Sales"
                    }
                  },
                  "Property": "Net Revenue"
                }
              },
              "queryRef": "Sales.Net Revenue",
              "nativeQueryRef": "Net Revenue"
            }
          ]
        }
      },
      "sortDefinition": {
        "sort": [
          {
            "field": {
              "Column": {
                "Expression": {
                  "SourceRef": {
                    "Entity": "Date"
                  }
                },
                "Property": "Year Month Short"
              }
            },
            "direction": "Ascending"
          }
        ],
        "isDefaultSort": true
      }
    },
    "drillFilterOtherVisuals": true,
    "visualContainerObjects": {
      "title": [
        {
          "properties": {
            "text": {
              "expr": {
                "Literal": {
                  "Value": "'Revenue Trend'"
                }
              }
            },
            "fontSize": {
              "expr": {
                "Literal": {
                  "Value": "8D"
                }
              }
            },
            "fontFamily": {
              "expr": {
                "Literal": {
                  "Value": "''Segoe UI', wf_segoe-ui_normal, helvetica, arial, sans-serif'"
                }
              }
            }
          }
        }
      ]
    },
    "objects": {
      "categoryAxis": [
        {
          "properties": {
            "fontSize": {
              "expr": {
                "Literal": {
                  "Value": "8D"
                }
              }
            },
            "fontFamily": {
              "expr": {
                "Literal": {
                  "Value": "''Segoe UI', wf_segoe-ui_normal, helvetica, arial, sans-serif'"
                }
              }
            }
          }
        }
      ],
      "valueAxis": [
        {
          "properties": {
            "fontSize": {
              "expr": {
                "Literal": {
                  "Value": "8D"
                }
              }
            },
            "fontFamily": {
              "expr": {
                "Literal": {
                  "Value": "''Segoe UI', wf_segoe-ui_normal, helvetica, arial, sans-serif'"
                }
              }
            }
          }
        }
      ],
      "labels": [
        {
          "properties": {
            "fontSize": {
              "expr": {
                "Literal": {
                  "Value": "8D"
                }
              }
            },
            "fontFamily": {
              "expr": {
                "Literal": {
                  "Value": "''Segoe UI', wf_segoe-ui_normal, helvetica, arial, sans-serif'"
                }
              }
            }
          }
        }
      ],
      "legend": [
        {
          "properties": {
            "fontSize": {
              "expr": {
                "Literal": {
                  "Value": "8D"
                }
              }
            },
            "fontFamily": {
              "expr": {
                "Literal": {
                  "Value": "''Segoe UI', wf_segoe-ui_normal, helvetica, arial, sans-serif'"
                }
              }
            }
          }
        }
      ]
    }
  },
  "filterConfig": {
    "filters": [
      {
        "name": "5267c3ff8e8abadc460c",
        "field": {
          "Column": {
            "Expression": {
              "SourceRef": {
                "Entity": "Date"
              }
            },
            "Property": "Year Month Short"
          }
        },
        "type": "Categorical"
      },
      {
        "name": "4662222d2f3c3f299db0",
        "field": {
          "Measure": {
            "Expression": {
              "SourceRef": {
                "Entity": "Sales"
              }
            },
            "Property": "Net Revenue"
          }
        },
        "type": "Categorical"
      }
    ]
  }
}