{
  "$schema": "https://developer.microsoft.com/json-schemas/fabric/item/report/definition/visualContainer/2.7.0/schema.json",
  "name": "e81bdea5aa3ba09ae65b",
  "position": {
    "x": 850,
    "y": 160,
    "z": 11000,
    "height": 260,
    "width": 420,
    "tabOrder": 11000
  },
  "visual": {
    "visualType": "clusteredBarChart",
    "query": {
      "queryState": {
        "Category": {
          "projections": [
            {
              "field": {
                "Column": {
                  "Expression": {
                    "SourceRef": {
                      "Entity": "Customer"
                    }
                  },
                  "Property": "Country"
                }
              },
              "queryRef": "Customer.Country",
              "nativeQueryRef": "Country",
              "active": true
            }
          ]
        },
        "Y": {
          "projections": [
            {
              "field": {
                "Measure": {
                  "Expression": {
                    "SourceRef": {
                      "Entity": "Sales"
                    }
                  },
                  "Property": "Net Revenue"
                }
              },
              "queryRef": "Sales.Net Revenue",
              "nativeQueryRef": "Net Revenue"
            }
          ]
        }
      },
      "sortDefinition": {
        "sort": [
          {
            "field": {
              "Column": {
                "Expression": {
                  "SourceRef": {
                    "Entity": "Customer"
                  }
                },
                "Property": "Country"
              }
            },
            "direction": "Ascending"
          }
        ],
        "isDefaultSort": true
      }
    },
    "drillFilterOtherVisuals": true,
    "visualContainerObjects": {
      "title": [
        {
          "properties": {
            "text": {
              "expr": {
                "Literal": {
                  "Value": "'Revenue by Country'"
                }
              }
            },
            "fontSize": {
              "expr": {
                "Literal": {
                  "Value": "8D"
                }
              }
            },
            "fontFamily": {
              "expr": {
                "Literal": {
                  "Value": "''Segoe UI', wf_segoe-ui_normal, helvetica, arial, sans-serif'"
                }
              }
            }
          }
        }
      ]
    },
    "objects": {
      "categoryAxis": [
        {
          "properties": {
            "fontSize": {
              "expr": {
                "Literal": {
                  "Value": "8D"
                }
              }
            },
            "fontFamily": {
              "expr": {
                "Literal": {
                  "Value": "''Segoe UI', wf_segoe-ui_normal, helvetica, arial, sans-serif'"
                }
              }
            }
          }
        }
      ],
      "valueAxis": [
        {
          "properties": {
            "fontSize": {
              "expr": {
                "Literal": {
                  "Value": "8D"
                }
              }
            },
            "fontFamily": {
              "expr": {
                "Literal": {
                  "Value": "''Segoe UI', wf_segoe-ui_normal, helvetica, arial, sans-serif'"
                }
              }
            }
          }
        }
      ],
      "labels": [
        {
          "properties": {
            "fontSize": {
              "expr": {
                "Literal": {
                  "Value": "8D"
                }
              }
            },
            "fontFamily": {
              "expr": {
                "Literal": {
                  "Value": "''Segoe UI', wf_segoe-ui_normal, helvetica, arial, sans-serif'"
                }
              }
            }
          }
        }
      ],
      "legend": [
        {
          "properties": {
            "fontSize": {
              "expr": {
                "Literal": {
                  "Value": "8D"
                }
              }
            },
            "fontFamily": {
              "expr": {
                "Literal": {
                  "Value": "''Segoe UI', wf_segoe-ui_normal, helvetica, arial, sans-serif'"
                }
              }
            }
          }
        }
      ]
    }
  },
  "filterConfig": {
    "filters": [
      {
        "name": "eca03f4d9548fbd0ba55",
        "field": {
          "Column": {
            "Expression": {
              "SourceRef": {
                "Entity": "Customer"
              }
            },
            "Property": "Country"
          }
        },
        "type": "Categorical"
      },
      {
        "name": "31595747ec7f2ab966f1",
        "field": {
          "Measure": {
            "Expression": {
              "SourceRef": {
                "Entity": "Sales"
              }
            },
            "Property": "Net Revenue"
          }
        },
        "type": "Categorical"
      }
    ]
  }
}